document_parse/__init__.py
document_parse/llamaparse.py
document_parse/main_file_s3_to_llamaparse.py
syia_mcp_all_servers_2025_x7k9-0.1.4.dist-info/METADATA
syia_mcp_all_servers_2025_x7k9-0.1.4.dist-info/WHEEL
syia_mcp_all_servers_2025_x7k9-0.1.4.dist-info/top_level.txt
syia_mcp_all_servers_2025_x7k9-0.1.4.dist-info/RECORD
