Metadata-Version: 2.4
Name: syia-mcp-all-servers-2025-x7k9
Version: 0.1.4
Summary: Meta package for all MCP servers
Requires-Python: >=3.12
Requires-Dist: syia-mcp-navigation-equipment-manuals-2025-x7k9
Requires-Dist: syia-mcp-crew-2025-x7k9
Requires-Dist: syia-mcp-maker-circulars-2025-x7k9
Requires-Dist: syia-mcp-purchase-2025-x7k9
Requires-Dist: syia-mcp-pms-2025-x7k9
Requires-Dist: syia-mcp-defect-2025-x7k9
Requires-Dist: syia-mcp-voyage-2025-x7k9
Requires-Dist: syia-mcp-company-specific-docs-2025-x7k9
Requires-Dist: syia-mcp-imo-publications-2025-x7k9
Requires-Dist: syia-mcp-casefile-2025-x7k9
